response_bandwidth_limiter/__init__.py
response_bandwidth_limiter/decorator.py
response_bandwidth_limiter/errors.py
response_bandwidth_limiter/limiter.py
response_bandwidth_limiter/middleware.py
response_bandwidth_limiter/util.py
response_bandwidth_limiter-0.1.0.dist-info/LICENSE
response_bandwidth_limiter-0.1.0.dist-info/METADATA
response_bandwidth_limiter-0.1.0.dist-info/WHEEL
response_bandwidth_limiter-0.1.0.dist-info/top_level.txt
response_bandwidth_limiter-0.1.0.dist-info/RECORD
