Metadata-Version: 2.2
Name: response-bandwidth-limiter
Version: 0.1.0
Summary: A simple response bandwidth limiting extension for FastAPI and Starlette
Author-email: kirisaki77 <110320276+kirisaki77@users.noreply.github.com>
Project-URL: Homepage, https://github.com/kirisaki77/response-bandwidth-limiter
Classifier: Programming Language :: Python :: 3
Classifier: License :: OSI Approved :: Mozilla Public License 2.0 (MPL 2.0)
Classifier: Operating System :: OS Independent
Requires-Python: >=3.6
License-File: LICENSE
Requires-Dist: asyncio>=3.4.3
Provides-Extra: dev
Requires-Dist: pytest>=6.0.0; extra == "dev"
Requires-Dist: httpx>=0.20.0; extra == "dev"
Requires-Dist: fastapi>=0.68.0; extra == "dev"
Requires-Dist: starlette>=0.14.0; extra == "dev"
